gcp_mcp_server/__init__.py
gcp_mcp_server/server.py
gcp_mcp_server-0.1.0.dist-info/METADATA
gcp_mcp_server-0.1.0.dist-info/WHEEL
gcp_mcp_server-0.1.0.dist-info/entry_points.txt
gcp_mcp_server-0.1.0.dist-info/top_level.txt
gcp_mcp_server-0.1.0.dist-info/RECORD
