Metadata-Version: 2.2
Name: gcp-mcp-server
Version: 0.1.0
Summary: An MCP server providing tools for GCP Cloud Functions logs
Author: Lee
Project-URL: Homepage, https://github.com/lee/gcp-mcp-server
Project-URL: Bug Tracker, https://github.com/lee/gcp-mcp-server/issues
Classifier: Programming Language :: Python :: 3
Classifier: Programming Language :: Python :: 3.10
Classifier: Programming Language :: Python :: 3.11
Classifier: Programming Language :: Python :: 3.12
Classifier: License :: OSI Approved :: MIT License
Classifier: Operating System :: OS Independent
Requires-Python: >=3.10
Requires-Dist: anyio>=4.5
Requires-Dist: click>=8.1.0
Requires-Dist: mcp>=0.1.0
Requires-Dist: google-cloud-logging>=3.9.0
Requires-Dist: google-cloud-functions>=1.15.0
Requires-Dist: uvicorn>=0.27.0
Requires-Dist: starlette>=0.36.0
Dynamic: requires-python
